ArcanePythonModule/__init__.py
ArcanePythonModule/ECS/Components.py
ArcanePythonModule/ECS/Entity.py
ArcanePythonModule/ECS/__init__.py
ArcanePythonModule/Maths/Vector.py
ArcanePythonModule/Maths/__init__.py
ArcanePython-0.0.3.dist-info/METADATA
ArcanePython-0.0.3.dist-info/WHEEL
ArcanePython-0.0.3.dist-info/top_level.txt
ArcanePython-0.0.3.dist-info/RECORD
