Metadata-Version: 2.1
Name: ArcanePython
Version: 0.0.3
Summary: Arcane Scripting Package
Author: Thomas Heeley
Keywords: python
Classifier: Development Status :: 1 - Planning
Classifier: Intended Audience :: Developers
Classifier: Programming Language :: Python :: 3
Classifier: Operating System :: Unix
Classifier: Operating System :: MacOS :: MacOS X
Classifier: Operating System :: Microsoft :: Windows
